{
    "symbols": {
        "$start_memory": 12288,
        "$VIDEO_MEM": 12289,
        "$INT_VECTORS": 12290,
        "$SYSCALL_RETURN_VALUE": 12291,
        "$SYSCALL_RETURN_STATUS": 12292,
        "$DATASTACK": 12293,
        "$DATASTACK_PTR": 12309,
        "$DATASTACK_INDEX": 12310,
        "$WELCOME_MESSAGE": 12311,
        "@init_interrupt_vector_table": 8,
        "@error_invalid_cmd": 12,
        "$string_invalid_cmd": 12331,
        "@error_wrong_filename": 15,
        "$string_wrong_filename": 12344,
        "@error_fatal_disk_error": 18,
        "$string_disk_error": 12360,
        "@print_error_string": 24,
        "$cursor_x": 12378,
        "$cursor_y": 12379,
        "@print_char": 32,
        "@clear_screen": 67,
        "@scroll_screen": 78,
        "@print_cursor": 96,
        "@del_cursor": 104,
        "@print_number": 112,
        "$KBD_READ_PNTR": 12380,
        "$KBD_WRITE_PNTR": 12381,
        "$KBD_BUFFER": 12382,
        "$KBD_BUFFER_ADRES": 12398,
        "$KBD_IO_BASE_POINTER": 12399,
        "@KBD_INIT": 157,
        "@KBD_ISR": 163,
        "@KBD_GET_CHAR": 179,
        "$status_register": 12272,
        "$command_register": 12273,
        "$hostbuffer_adres_register": 12274,
        "$filehash_register": 12275,
        "$last_block_register": 12276,
        "$disk_io_buffer": 12400,
        "$modulo": 12413,
        "$filename_pointer": 12414,
        "$temp_hash": 12415,
        "@init_vdisk": 195,
        "@open_file_read": 209,
        "@open_file_write": 227,
        "@read_file_block": 245,
        "@close_file": 259,
        "@hash_filename": 273,
        "@_check_return_status": 293,
        "$kernel_prompt": 12416,
        "@init_kernel": 1024,
        "@main_loop": 1030,
        "@init_kernel_syscalls": 1037,
        "@sys_exit": 1074,
        "@sys_print_char": 1076,
        "@sys_clear_screen": 1078,
        "@sys_get_char": 1080,
        "@sys_print_string": 1088,
        "@sys_print_cursor": 1096,
        "@sys_del_cursor": 1098,
        "@sys_print_number": 1100,
        "@sys_f_open_read": 1102,
        "@sys_f_read_block": 1112,
        "@sys_f_close": 1123,
        "@sys_f_open_write": 1125,
        "$CMD_BUFFER_BASE": 12420,
        "$CMD_BUFFER": 12421,
        "$CMD_BUFFER_PTR": 12501,
        "$STACKS_VARS": 12502,
        "$STACKS_VARS_BASE": 12528,
        "@cli_cmd_cls": 1135,
        "@cli_cmd_quit": 1138,
        "@cli_main_loop": 1140,
        "@execute_command_buffer": 1188,
        "@push_A": 1213,
        "@pop_A": 1216,
        "@push_B": 1219,
        "@pop_B": 1222,
        "@rt_add": 1225,
        "@rt_print_tos": 1230,
        "@rt_next": 1238,
        "@rt_store_var": 1241,
        "@rt_restore_var": 1253,
        "$line_to_print": 12529,
        "@rt_stacks_cmd_list": 1265,
        "@rt_stacks_cmd_run": 1302,
        "@rt_stacks_cmd_load": 1325,
        "$test_filename": 12530,
        "@rt_stacks_cmd_save": 1348,
        "$PROG_BUFFER_WRITE_PTR": 12538,
        "$PROG_BUFFER_TEMP_PTR": 12539,
        "@load_block_to_prog_buffer": 1362,
        "$PROG_BUFFER": 4096,
        "$PROG_BUFFER_BASE": 12540,
        "$PROG_BUFFER_PTR": 12541,
        "$LINE_INDEX_ARRAY": 12542,
        "$LINE_INDEX_ARRAY_BASE": 12606,
        "$LINE_NUMBER": 12607,
        "$STACKS_WELCOME_MSG": 12608,
        "@interpreter_start": 1391,
        "@stacks_main_loop": 1408,
        "@print_line_number": 1491,
        "$TOKEN_TYPE": 12633,
        "$TOKEN_VALUE": 12634,
        "$TOKEN_ID": 12635,
        "$TOKEN_BUFFER_BASE": 12636,
        "$CMD_BUFFER_SCAN_PTR": 12637,
        "$current_part": 12638,
        "$current_part_base": 12663,
        "$current_part_ptr": 12664,
        "@init_tokenizer_buffer": 1494,
        "@get_next_token": 1497,
        "@is_numeric": 1586,
        "$CMD_TABLE": 12665,
        "$CMD_TABLE_BASE": 12681,
        "$STR_TABLE": 12682,
        "$STR_TABLE_BASE": 12698,
        "$ID_TABLE": 12699,
        "$ID_TABLE_BASE": 12715,
        "$LUT_INDEX": 12716,
        "$CMD_CLS_STR": 12717,
        "$CMD_QUIT_STR": 12721,
        "$CMD_STACKS_STR": 12726,
        "$CMD_LIST_STR": 12733,
        "$CMD_RUN_STR": 12738,
        "$CMD_LOAD_STR": 12742,
        "$CMD_SAVE_STR": 12747,
        "$RT_ADD_STR": 12752,
        "$RT_PRINT_STR": 12754,
        "$RT_STORE_VAR": 12756,
        "$RT_RESTORE_VAR": 12758,
        "$RT_NEXT_STR": 12760
    },
    "labels": [
        {
            ":end_warning": 21,
            ":end_fatal": 22,
            ":end_less": 22,
            ":loop": 24,
            ":end_loop": 31,
            ":do_print_Return": 39,
            ":do_print_BackSpace": 42,
            ":do_print_char": 51,
            ":check_bounderies": 60,
            ":print_char_done": 64,
            ":clear_loop": 69,
            ":scroll_screen_loop": 81,
            ":scroll_screen_blank_loop": 91,
            ":is_positive": 131,
            ":divide_loop": 132,
            ":print_loop": 138,
            ":print_zero": 146,
            ":print_number_done": 148,
            ":end_kbd_isr": 178,
            ":no_char": 193,
            ":disk_init_loop": 195,
            ":disk_init_wait_loop": 202,
            ":disk_init_done": 208,
            ":open_read_success": 220,
            ":open_read_error": 223,
            ":open_file_read_end": 226,
            ":open_write_success": 238,
            ":open_write_error": 241,
            ":open_file_write_end": 244,
            ":read_block_success": 254,
            ":read_block_error": 256,
            ":read_block_end": 258,
            ":close_file_success": 268,
            ":close_file_error": 270,
            ":close_file_end": 272,
            ":hash_loop": 278,
            ":end_hash_return": 289,
            ":return_succes_status": 303,
            ":return_file_error_status": 305,
            ":return_disk_error_status": 308
        },
        {
            ":set_status_true": 1084,
            ":loop": 1088,
            ":end_loop": 1095,
            ":f_open_read_file_error": 1108,
            ":f_read_block_error": 1119,
            ":f_open_write_file_error": 1131,
            ":char_available": 1146,
            ":store_char_in_buffer": 1148,
            ":cli_handle_backspace": 1162,
            ":cli_process_command_buffer": 1171,
            ":executor_loop": 1188,
            ":execute_cmd_token": 1201,
            ":execute_num_token": 1204,
            ":execute_var_token": 1207,
            ":execute_unknown_token": 1210,
            ":executor_loop_end": 1212,
            ":store_var_no_var": 1252,
            ":restore_var_no_var": 1264,
            ":list_loop": 1273,
            ":print_line_loop": 1283,
            ":print_line_end": 1291,
            ":list_loop_end": 1298,
            ":debug1": 1302,
            ":run_loop": 1310,
            ":run_loop_end": 1321,
            ":read_loop": 1335,
            ":debug": 1343,
            ":close_and_end": 1345,
            ":cmd_load_end": 1347,
            ":write_loop": 1358,
            ":close_and_save_end": 1359,
            ":cmd_save_end": 1361,
            ":copy_loop": 1365,
            ":read_next": 1373,
            ":copy_loop_end": 1375,
            ":write_line_number": 1382,
            ":init_interpreter_state": 1397,
            ":stacks_input_loop": 1415,
            ":stacks_char_available": 1421,
            ":stacks_store_char_in_buffer": 1423,
            ":do_store_char": 1436,
            ":stacks_handle_backspace": 1446,
            ":stacks_process_line_buffer": 1455,
            ":stacks_handle_esc": 1467,
            ":stacks_cmd_input_loop": 1472,
            ":stacks_cmd_available": 1478,
            ":handle_stacks_cmd_exit": 1486,
            ":handle_stacks_cmd_list": 1487,
            ":handle_stacks_cmd_run": 1489,
            ":skip_loop": 1497,
            ":found_token_start": 1507,
            ":parse_loop": 1508,
            ":end_token": 1523,
            ":classify_token": 1527,
            ":str_table_loop": 1528,
            ":current_part_loop": 1535,
            ":return_cmd_token": 1546,
            ":check_for_var_or_numeric": 1551,
            ":check_for_numeric": 1572,
            ":return_unknown_token": 1580,
            ":return_no_token": 1583,
            ":check_neg_sign": 1590,
            ":check_pos_sign": 1596,
            ":is_numeric_loop": 1602,
            ":check_digit": 1604,
            ":handle_valid_digit": 1611,
            ":is_numeric_yes": 1617,
            ":is_numeric_no": 1621
        }
    ]
}